[{"Word":"characters","Notes":"2. Possibly a hidden word indicator."},{"Word":"content","Notes":"2. Possibly a hidden word indicator."},{"Word":"contents","Notes":"2. Possibly a hidden word indicator."},{"Word":"contributing","Notes":"Possibly a hidden word indicator."},{"Word":"displaying","Notes":"Possibly a hidden word indicator."},{"Word":"exhibiting","Notes":"Possibly a hidden word indicator."},{"Word":"extract","Notes":"Possibly a hidden word indicator."},{"Word":"featuring","Notes":"Possibly a hidden word indicator."},{"Word":"from","Notes":"Possibly a hidden word indicator."},{"Word":"helping to make","Notes":"Possibly a hidden word indicator."},{"Word":"hidden","Notes":"Possibly a hidden word indicator."},{"Word":"hides","Notes":"Possibly a hidden word indicator."},{"Word":"hiding","Notes":"2. Possibly a hidden word indicator."},{"Word":"in","Notes":"2. Possibly a hidden word indicator."},{"Word":"letters","Notes":"2. Possibly a hidden word indicator."},{"Word":"of","Notes":"Possibly a hidden word indicator."},{"Word":"part","Notes":"Possibly a hidden word indicator."},{"Word":"partial","Notes":"Possibly a hidden word indicator."},{"Word":"partly","Notes":"Possibly a hidden word indicator."},{"Word":"providing","Notes":"Possibly a hidden word indicator."},{"Word":"secreting","Notes":"Possibly a hidden word indicator."},{"Word":"selection","Notes":"Possibly a hidden word indicator."},{"Word":"showing","Notes":"Possibly a hidden word indicator."},{"Word":"smuggling","Notes":"Possibly a hidden word indicator."},{"Word":"some","Notes":"Possibly a hidden word indicator."},{"Word":"somewhat","Notes":"Possibly a hidden word indicator."},{"Word":"swallowed","Notes":"2. Possibly a hidden word indicator."},{"Word":"veiled","Notes":"Possibly a hidden word indicator."},{"Word":"within","Notes":"2. Possibly a hidden word indicator."},{"Word":"wrapped","Notes":"2. Possibly a hidden word indicator."}]